amy/__init__.py
amy/amy.py
amy/console.py
amy/test_string.py
amy_py-0.0.7.dist-info/LICENSE
amy_py-0.0.7.dist-info/METADATA
amy_py-0.0.7.dist-info/WHEEL
amy_py-0.0.7.dist-info/top_level.txt
amy_py-0.0.7.dist-info/RECORD
